[
  {
    "href": "https://www.bilibili.com/video/BV18K411e7sr?p=1",
    "title": "【主线】序",
    "tag": "主线",
    "character": "N/A",
    "timestamp": "N/A"
  },
  {
    "href": "https://www.bilibili.com/video/BV18K411e7sr?p=2",
    "title": "【主线】残酷节目",
    "tag": "主线",
    "character": "N/A",
    "timestamp": "N/A"
  },
  {
    "href": "https://www.bilibili.com/video/BV18K411e7sr?p=3",
    "title": "【主线】重返现实（上）",
    "tag": "主线",
    "character": "N/A",
    "timestamp": "N/A"
  },
  {
    "href": "https://www.bilibili.com/video/BV18K411e7sr?p=4",
    "title": "【密室】人偶之匣（上）",
    "tag": "密室",
    "character": "N/A",
    "timestamp": "N/A"
  },
  {
    "href": "https://www.bilibili.com/video/BV18K411e7sr?p=5",
    "title": "【支线】世界树果实",
    "tag": "支线",
    "character": "N/A",
    "timestamp": "N/A"
  },
  {
    "href": "https://www.bilibili.com/video/BV18K411e7sr?p=6",
    "title": "【主线】重返现实（中）",
    "tag": "主线",
    "character": "N/A",
    "timestamp": "N/A"
  },
  {
    "href": "https://www.bilibili.com/video/BV18K411e7sr?p=7",
    "title": "【支线】爱莎医院的黑幕",
    "tag": "支线",
    "character": "N/A",
    "timestamp": "N/A"
  },
  {
    "href": "https://www.bilibili.com/video/BV18K411e7sr?p=8",
    "title": "【支线】北陆风雪",
    "tag": "支线",
    "character": "N/A",
    "timestamp": "N/A"
  },
  {
    "href": "https://www.bilibili.com/video/BV18K411e7sr?p=9",
    "title": "【主线】重返现实（下）",
    "tag": "主线",
    "character": "N/A",
    "timestamp": "N/A"
  },
  {
    "href": "https://www.bilibili.com/video/BV18K411e7sr?p=10",
    "title": "【主线】独裁者的游戏",
    "tag": "主线",
    "character": "N/A",
    "timestamp": "N/A"
  },
  {
    "href": "https://www.bilibili.com/video/BV18K411e7sr?p=11",
    "title": "【主线】休息时间",
    "tag": "主线",
    "character": "N/A",
    "timestamp": "N/A"
  },
  {
    "href": "https://www.bilibili.com/video/BV18K411e7sr?p=12",
    "title": "【密室】人偶之匣（下）",
    "tag": "密室",
    "character": "N/A",
    "timestamp": "N/A"
  },
  {
    "href": "https://www.bilibili.com/video/BV18K411e7sr?p=13",
    "title": "【密室】迷失空间",
    "tag": "密室",
    "character": "N/A",
    "timestamp": "N/A"
  },
  {
    "href": "https://www.bilibili.com/video/BV18K411e7sr?p=14",
    "title": "【支线】污名",
    "tag": "支线",
    "character": "N/A",
    "timestamp": "N/A"
  },
  {
    "href": "https://www.bilibili.com/video/BV18K411e7sr?p=15",
    "title": "【支线】影响力比拼",
    "tag": "支线",
    "character": "N/A",
    "timestamp": "N/A"
  },
  {
    "href": "https://www.bilibili.com/video/BV18K411e7sr?p=16",
    "title": "【支线】东水幻术",
    "tag": "支线",
    "character": "N/A",
    "timestamp": "N/A"
  },
  {
    "href": "https://www.bilibili.com/video/BV18K411e7sr?p=17",
    "title": "【支线】重拾神王明珠",
    "tag": "支线",
    "character": "N/A",
    "timestamp": "N/A"
  },
  {
    "href": "https://www.bilibili.com/video/BV18K411e7sr?p=18",
    "title": "【支线】沉冤昭雪",
    "tag": "支线",
    "character": "N/A",
    "timestamp": "N/A"
  },
  {
    "href": "https://www.bilibili.com/video/BV18K411e7sr?p=19",
    "title": "【支线】心想事成",
    "tag": "支线",
    "character": "N/A",
    "timestamp": "N/A"
  },
  {
    "href": "https://www.bilibili.com/video/BV18K411e7sr?p=20",
    "title": "【密室】密室综艺",
    "tag": "密室",
    "character": "N/A",
    "timestamp": "N/A"
  },
  {
    "href": "https://www.bilibili.com/video/BV18K411e7sr?p=21",
    "title": "【主线】天地无束",
    "tag": "主线",
    "character": "N/A",
    "timestamp": "N/A"
  },
  {
    "href": "https://www.bilibili.com/video/BV18K411e7sr?p=22",
    "title": "【支线】云外至宝",
    "tag": "支线",
    "character": "N/A",
    "timestamp": "N/A"
  },
  {
    "href": "https://www.bilibili.com/video/BV18K411e7sr?p=23",
    "title": "【生日】生日通话",
    "tag": "生日",
    "character": "N/A",
    "timestamp": "N/A"
  },
  {
    "href": "https://www.bilibili.com/video/BV18K411e7sr?p=24",
    "title": "【新春】新春电话",
    "tag": "新春",
    "character": "N/A",
    "timestamp": "N/A"
  },
  {
    "href": "https://www.bilibili.com/video/BV18K411e7sr?p=25",
    "title": "【活动】心动时刻",
    "tag": "活动",
    "character": "N/A",
    "timestamp": "N/A"
  },
  {
    "href": "https://www.bilibili.com/video/BV18K411e7sr?p=26",
    "title": "【支线】含香教之危",
    "tag": "支线",
    "character": "N/A",
    "timestamp": "N/A"
  }
]
